{
    "customer": {
        "name": null,
        "age": 89,
        "gender": "male",
        "address": "10353 Hernandez Inlet Suite 738, East Paulmouth, OR 82548",
        "phone": "001-723-695-3961x63961",
        "email": "aleon@example.com",
        "account": {
            "account_number": "5b8fb1d0-2507-4de1-84c6-aa8cfad5ad66",
            "balance": 42131.92,
            "transactions": [
                {
                    "date": "2024-06-10",
                    "description": "Withdrawal",
                    "amount": -1855.29,
                    "transaction_id": 75171711
                },
                {
                    "date": "2023-01-23",
                    "description": "Withdrawal",
                    "amount": -2382.97,
                    "transaction_id": 6398367
                }
            ]
        }
    }
}