{
    "customer": {
        "name": null,
        "age": 18,
        "gender": "male",
        "address": "4222 Tina Landing Apt. 619, Johnsonport, RI 11651",
        "phone": "+1-233-773-5424x871",
        "email": "nsmith@example.org",
        "account": {
            "account_number": "bc7bc778-599b-4f15-92f0-d67f40f793a7",
            "balance": 16314.06,
            "transactions": [
                {
                    "date": "2023-01-23",
                    "description": "Withdrawal",
                    "amount": 2961.44,
                    "transaction_id": 95718665
                }
            ]
        }
    }
}