{
    "customer": {
        "name": "Rachel Robertson",
        "age": 38,
        "gender": "female",
        "address": "40695 Joshua Pines Suite 604, Jodiview, AK 50043",
        "phone": "001-496-923-8371x593",
        "email": "harrisfrank@example.net",
        "account": {
            "account_number": "030c6280-74be-41e3-8487-94043fec8f74",
            "balance": 17135.64,
            "transactions": [
                {
                    "date": "2023-11-04",
                    "description": "Deposit",
                    "amount": 31090.42,
                    "transaction_id": 114484766
                },
                {
                    "date": "2023-10-24",
                    "description": "Withdrawal",
                    "amount": 41874.54,
                    "transaction_id": 79175345
                },
                {
                    "date": "2024-06-28",
                    "description": "Deposit",
                    "amount": 31377.77,
                    "transaction_id": 114570130
                },
                {
                    "date": "2022-10-19",
                    "description": "Withdrawal",
                    "amount": 26868.26,
                    "transaction_id": 13692277
                }
            ]
        }
    }
}