{
    "customer": {
        "name": "Miranda Barnett",
        "age": 79,
        "gender": "male",
        "email": "irobinson@example.net",
        "account": {
            "account_number": "0a27247e-ea3b-4569-97d9-45f86b61a91e",
            "balance": 19151.01,
            "transactions": [
                {
                    "date": "2024-03-26",
                    "description": "Fee",
                    "amount": 4814.59,
                    "transaction_id": 430394443
                },
                {
                    "date": "2023-09-25",
                    "description": "Purchase",
                    "amount": 3202.68,
                    "transaction_id": 980353243
                },
                {
                    "date": "2023-12-03",
                    "description": "Fee",
                    "amount": 4034.63,
                    "transaction_id": 180020465
                },
                {
                    "date": "2024-08-23",
                    "description": "Interest",
                    "amount": 2335.58,
                    "transaction_id": 890635333
                },
                {
                    "date": "2024-01-21",
                    "description": "Refund",
                    "amount": 633.19,
                    "transaction_id": 940896298
                },
                {
                    "date": "2024-09-11",
                    "description": "Fee",
                    "amount": 2196.71,
                    "transaction_id": 184720904
                },
                {
                    "date": "2023-12-03",
                    "description": "Refund",
                    "amount": 3635.11,
                    "transaction_id": 609241837
                },
                {
                    "date": "2024-04-25",
                    "description": "Interest",
                    "amount": 3845.88,
                    "transaction_id": 118773365
                },
                {
                    "date": "2023-12-31",
                    "description": "Interest",
                    "amount": 4346.01,
                    "transaction_id": 199309421
                },
                {
                    "date": "2024-07-11",
                    "description": "Fee",
                    "amount": 2811.54,
                    "transaction_id": 946423812
                },
                {
                    "date": "2024-01-13",
                    "description": "Interest",
                    "amount": 206.85,
                    "transaction_id": 150911112
                },
                {
                    "date": "2024-05-10",
                    "description": "Fee",
                    "amount": 3629.0,
                    "transaction_id": 796817784
                },
                {
                    "date": "2024-06-26",
                    "description": "Fee",
                    "amount": 4453.14,
                    "transaction_id": 426104016
                },
                {
                    "date": "2024-07-14",
                    "description": "Interest",
                    "amount": 94.5,
                    "transaction_id": 946280271
                },
                {
                    "date": "2024-02-01",
                    "description": "Interest",
                    "amount": 2475.6,
                    "transaction_id": 376332100
                },
                {
                    "date": "2024-06-07",
                    "description": "Interest",
                    "amount": 3847.63,
                    "transaction_id": 725322143
                },
                {
                    "date": "2023-11-26",
                    "description": "Fee",
                    "amount": 1267.33,
                    "transaction_id": 833207626
                },
                {
                    "date": "2024-02-22",
                    "description": "Fee",
                    "amount": 3143.83,
                    "transaction_id": 372643919
                },
                {
                    "date": "2024-01-19",
                    "description": "Fee",
                    "amount": 797.64,
                    "transaction_id": 700016041
                },
                {
                    "date": "2024-03-30",
                    "description": "Purchase",
                    "amount": 2659.78,
                    "transaction_id": 471856330
                },
                {
                    "date": "2024-09-06",
                    "description": "Refund",
                    "amount": 679.82,
                    "transaction_id": 272039745
                },
                {
                    "date": "2024-06-29",
                    "description": "Purchase",
                    "amount": 3645.23,
                    "transaction_id": 408787277
                },
                {
                    "date": "2024-07-24",
                    "description": "Purchase",
                    "amount": -297.06,
                    "transaction_id": 217910176
                }
            ]
        }
    }
}