{
    "customer": {
        "name": "Elizabeth Acosta",
        "age": 41,
        "gender": "male",
        "address": "147 Hartman Ports, New Jessicaborough, MT 12873",
        "phone": "(285)797-4745x60539",
        "email": "aaron40@example.net",
        "account": {
            "account_number": "6b9f7172-7f6d-403a-a961-89c35deb223d",
            "balance": -8281.2,
            "transactions": [
                {
                    "date": "2022-11-22",
                    "description": "Withdrawal",
                    "amount": 1701.61,
                    "transaction_id": 73914217
                },
                {
                    "date": "2023-06-05",
                    "description": "Withdrawal",
                    "amount": 4313.52,
                    "transaction_id": 16182447
                },
                {
                    "date": "2023-01-27",
                    "description": "Interest",
                    "amount": 2957.28,
                    "transaction_id": 95701840
                }
            ]
        }
    }
}