{
    "customer": {
        "name": "Katherine Sellers",
        "age": 84,
        "gender": "female",
        "address": "5491 Jeffrey Tunnel, Adamsville, SD 44548",
        "phone": "423.968.0534",
        "email": "rogersmackenzie@example.net",
        "account": {
            "account_number": "a34806bb-372b-4663-91eb-cc632f81e88a",
            "balance": 24574.19,
            "transactions": [
                {
                    "date": "2024-03-29",
                    "description": "Withdrawal",
                    "amount": 31086.88,
                    "transaction_id": 55213648
                },
                {
                    "date": "2023-10-24",
                    "description": "Interest",
                    "amount": 29428.73,
                    "transaction_id": 102792364
                },
                {
                    "date": "2023-03-26",
                    "description": "Deposit",
                    "amount": 15694.74,
                    "transaction_id": 6813870
                },
                {
                    "date": "2024-02-13",
                    "description": "Withdrawal",
                    "amount": 34085.78,
                    "transaction_id": 5106845
                }
            ]
        }
    }
}