{
    "customer": {
        "name": "Karen Golden",
        "age": 77,
        "gender": "male",
        "address": "642 Elizabeth Causeway, Jacksonstad, ND 56321",
        "phone": "(698)809-7648x668",
        "email": "greenduane@example.com",
        "account": {
            "account_number": "35b388ff-3d79-40ab-9bf4-6b6ea6428845",
            "balance": 8169.5,
            "transactions": [
                {
                    "date": "2024-02-17",
                    "description": "Fee",
                    "amount": 931.68,
                    "transaction_id": 624686607
                },
                {
                    "date": "2024-02-27",
                    "description": "Interest",
                    "amount": 3454.09,
                    "transaction_id": 407869081
                },
                {
                    "date": "2024-01-25",
                    "description": "Purchase",
                    "amount": 2011.69,
                    "transaction_id": 462407972
                },
                {
                    "date": "2024-03-10",
                    "description": "Purchase",
                    "amount": -355.45,
                    "transaction_id": 445098080
                },
                {
                    "date": "2023-12-17",
                    "description": "Interest",
                    "amount": 1604.49,
                    "transaction_id": 425515407
                },
                {
                    "date": "2024-04-02",
                    "description": "Interest",
                    "amount": 4952.56,
                    "transaction_id": 643483632
                },
                {
                    "date": "2024-03-24",
                    "description": "Purchase",
                    "amount": 1564.64,
                    "transaction_id": 833840311
                },
                {
                    "date": "2024-02-02",
                    "description": "Interest",
                    "amount": 1121.6,
                    "transaction_id": 768878194
                },
                {
                    "date": "2024-07-04",
                    "description": "Purchase",
                    "amount": 2556.06,
                    "transaction_id": 663494026
                },
                {
                    "date": "2024-06-16",
                    "description": "Purchase",
                    "amount": 3708.28,
                    "transaction_id": 806726848
                },
                {
                    "date": "2023-11-23",
                    "description": "Fee",
                    "amount": 2411.27,
                    "transaction_id": 115075625
                },
                {
                    "date": "2024-08-17",
                    "description": "Refund",
                    "amount": 1285.64,
                    "transaction_id": 714280547
                },
                {
                    "date": "2024-07-19",
                    "description": "Purchase",
                    "amount": 549.81,
                    "transaction_id": 722603954
                },
                {
                    "date": "2024-02-15",
                    "description": "Purchase",
                    "amount": 4001.58,
                    "transaction_id": 657923036
                },
                {
                    "date": "2024-01-29",
                    "description": "Fee",
                    "amount": 2731.19,
                    "transaction_id": 650689529
                },
                {
                    "date": "2024-07-08",
                    "description": "Refund",
                    "amount": 67.81,
                    "transaction_id": 200187697
                },
                {
                    "date": "2024-08-15",
                    "description": "Purchase",
                    "amount": -836.99,
                    "transaction_id": 364473831
                },
                {
                    "date": "2024-07-28",
                    "description": "Fee",
                    "amount": 2384.64,
                    "transaction_id": 854252017
                },
                {
                    "date": "2024-04-05",
                    "description": "Purchase",
                    "amount": 4989.81,
                    "transaction_id": 615628876
                },
                {
                    "date": "2024-03-08",
                    "description": "Refund",
                    "amount": 2219.67,
                    "transaction_id": 285663088
                },
                {
                    "date": "2023-09-14",
                    "description": "Purchase",
                    "amount": 3160.92,
                    "transaction_id": 860021167
                },
                {
                    "date": "2023-12-07",
                    "description": "Interest",
                    "amount": -768.33,
                    "transaction_id": 620676432
                }
            ]
        }
    }
}