{
    "customer": {
        "name": "Lisa Knight",
        "age": 74,
        "gender": "female",
        "address": "9585 Jennifer Forks, Port Christophertown, LA 75175",
        "phone": "(930)626-4307",
        "email": "yburton@example.org",
        "account": {
            "account_number": "f3cbe5fb-40c6-4d86-9a3e-e202d0f02fe8",
            "balance": 17524.61,
            "transactions": [
                {
                    "date": "2023-06-16",
                    "description": "Deposit",
                    "amount": 8550.29,
                    "transaction_id": 88897683
                },
                {
                    "date": "2024-07-13",
                    "description": "Deposit",
                    "amount": 43586.37,
                    "transaction_id": 119560949
                }
            ]
        }
    }
}