{
    "customer": {
        "name": "Anthony Erickson",
        "age": 58,
        "gender": "male",
        "address": "22253 Baird Springs, Robinsonville, LA 01036",
        "phone": "917-838-1055",
        "email": "justin81@example.com",
        "account": {
            "account_number": "6a9bee99-bcf1-4675-83d5-0d7531fee8b1",
            "balance": 32611.99,
            "transactions": [
                {
                    "date": "2023-04-15",
                    "description": "Interest",
                    "amount": 14314.15,
                    "transaction_id": 54804150
                }
            ]
        }
    }
}