{
    "customer": {
        "name": "Stacey Vargas",
        "gender": "male",
        "phone": "001-752-897-8454",
        "email": "daniel64@example.com",
        "account": {
            "account_number": "4581ccf7-adb0-40a0-92ae-46b5b5ea4ed8",
            "balance": 9629.1,
            "transactions": [
                {
                    "date": "2024-08-19",
                    "description": "Refund",
                    "amount": 4985.08,
                    "transaction_id": 803378899
                },
                {
                    "date": "2023-10-19",
                    "description": "Refund",
                    "amount": 3761.33,
                    "transaction_id": 323964254
                },
                {
                    "date": "2024-03-02",
                    "description": "Purchase",
                    "amount": 305.29,
                    "transaction_id": 183906916
                },
                {
                    "date": "2024-03-19",
                    "description": "Fee",
                    "amount": 217.02,
                    "transaction_id": 483619369
                },
                {
                    "date": "2024-05-12",
                    "description": "Fee",
                    "amount": 4555.52,
                    "transaction_id": 113197360
                },
                {
                    "date": "2023-12-23",
                    "description": "Interest",
                    "amount": 1527.9,
                    "transaction_id": 516369671
                },
                {
                    "date": "2024-08-13",
                    "description": "Fee",
                    "amount": 1584.22,
                    "transaction_id": 459477554
                },
                {
                    "date": "2024-09-04",
                    "description": "Refund",
                    "amount": 4811.68,
                    "transaction_id": 212592713
                },
                {
                    "date": "2024-02-22",
                    "description": "Refund",
                    "amount": 2159.57,
                    "transaction_id": 453437173
                },
                {
                    "date": "2023-10-07",
                    "description": "Purchase",
                    "amount": 48.02,
                    "transaction_id": 268003389
                },
                {
                    "date": "2023-10-13",
                    "description": "Fee",
                    "amount": 2841.11,
                    "transaction_id": 851758517
                },
                {
                    "date": "2023-12-08",
                    "description": "Purchase",
                    "amount": 3560.97,
                    "transaction_id": 298265676
                },
                {
                    "date": "2023-12-11",
                    "description": "Fee",
                    "amount": 1504.11,
                    "transaction_id": 766492192
                },
                {
                    "date": "2024-04-16",
                    "description": "Refund",
                    "amount": 4437.08,
                    "transaction_id": 545720158
                },
                {
                    "date": "2024-02-16",
                    "description": "Fee",
                    "amount": 1831.98,
                    "transaction_id": 967829032
                },
                {
                    "date": "2024-07-25",
                    "description": "Interest",
                    "amount": 86.07,
                    "transaction_id": 510928734
                },
                {
                    "date": "2023-10-25",
                    "description": "Fee",
                    "amount": 3833.32,
                    "transaction_id": 683885923
                },
                {
                    "date": "2024-01-23",
                    "description": "Interest",
                    "amount": 4001.8,
                    "transaction_id": 817741167
                },
                {
                    "date": "2024-02-10",
                    "description": "Fee",
                    "amount": 774.13,
                    "transaction_id": 859090515
                },
                {
                    "date": "2023-10-03",
                    "description": "Fee",
                    "amount": 1236.25,
                    "transaction_id": 947663228
                },
                {
                    "date": "2024-01-21",
                    "description": "Interest",
                    "amount": 3313.42,
                    "transaction_id": 576036565
                },
                {
                    "date": "2024-07-03",
                    "description": "Fee",
                    "amount": 242.15,
                    "transaction_id": 972086676
                },
                {
                    "date": "2024-08-31",
                    "description": "Purchase",
                    "amount": 1712.22,
                    "transaction_id": 126590644
                }
            ]
        }
    }
}