{
    "customer": {
        "name": "Joseph Mccarthy",
        "age": 42,
        "gender": "female",
        "address": "2472 Eddie Valleys Suite 668, West Kristyburgh, OH 97669",
        "phone": "651-875-3483x769",
        "email": "sanchezjoseph@example.com",
        "account": {
            "account_number": "c0ce928a-ac8e-4963-92d6-a11e99d6945a",
            "balance": 11931.9,
            "transactions": [
                {
                    "date": "2022-12-12",
                    "description": "Deposit",
                    "amount": 14715.17,
                    "transaction_id": 55196063
                }
            ]
        }
    }
}