{
    "customer": {
        "name": "Scott Thompson",
        "age": 42,
        "gender": "female",
        "address": "396 Martha Prairie, Kennedyborough, OR 57171",
        "phone": "001-532-218-3942",
        "email": "edwardsmary@example.net",
        "account": {
            "account_number": "2b413136-fcf7-4a7c-b295-eb5c44423242",
            "balance": 48058.63,
            "transactions": [
                {
                    "date": "2023-01-28",
                    "description": "Deposit",
                    "amount": 49198.19,
                    "transaction_id": 44044686
                },
                {
                    "date": "2024-02-15",
                    "description": "Interest",
                    "amount": 23677.24,
                    "transaction_id": 13897071
                }
            ]
        }
    }
}